{
  "id": "novena_to_the_divine_infant_king",
  "title": "Novena to the Divine Infant King",
  "description": "Embrace childlike holiness today. Pray to the Divine Infant King now and receive the gifts of humility, innocence, meekness, joy, and obedience to God’s will.",
  "category": "Devotion",
  "tags": [
    "Novena",
    "Devotion",
    "Novena to the Divine Infant King"
  ],
  "startRule": {
    "type": "fixed",
    "month": 3,
    "day": 17
  },
  "feastRule": {
    "type": "fixed",
    "month": 3,
    "day": 26
  },
  "source": {
    "url": "https://catholicnovenaapp.com/list-of-all-novenas/",
    "pageUrl": "https://catholicnovenaapp.com/novenas/divine-infant-king-novena/"
  },
  "days": [
    {
      "day": 1,
      "title": null,
      "prayer": null,
      "scripture": null,
      "reflection": null
    },
    {
      "day": 2,
      "title": null,
      "prayer": null,
      "scripture": null,
      "reflection": null
    },
    {
      "day": 3,
      "title": null,
      "prayer": null,
      "scripture": null,
      "reflection": null
    },
    {
      "day": 4,
      "title": null,
      "prayer": null,
      "scripture": null,
      "reflection": null
    },
    {
      "day": 5,
      "title": null,
      "prayer": null,
      "scripture": null,
      "reflection": null
    },
    {
      "day": 6,
      "title": null,
      "prayer": null,
      "scripture": null,
      "reflection": null
    },
    {
      "day": 7,
      "title": null,
      "prayer": null,
      "scripture": null,
      "reflection": null
    },
    {
      "day": 8,
      "title": null,
      "prayer": null,
      "scripture": null,
      "reflection": null
    },
    {
      "day": 9,
      "title": null,
      "prayer": null,
      "scripture": null,
      "reflection": null
    }
  ]
}
