{
  "id": "11-10_saint_andrew_avellini",
  "name": "Saint Andrew Avellini",
  "mmdd": "11-10",
  "feast": "The Tenth Day of November",
  "summary": "Trevor John Siemian is an American professional football quarterback for the Tennessee Titans of the National Football League (NFL). He played college football for the Northwestern Wildcats and was selected by the Denver Broncos in the seventh round of the 2015 NFL draft.",
  "biography": "Trevor John Siemian is an American professional football quarterback for the Tennessee Titans of the National Football League (NFL). He played college football for the Northwestern Wildcats and was selected by the Denver Broncos in the seventh round of the 2015 NFL draft. Siemian was part of the Broncos when they won Super Bowl 50, serving as the third-string quarterback behind starter Peyton Manning and backup Brock Osweiler. He has also been a member of the Minnesota Vikings, New York Jets, New Orleans Saints, Chicago Bears, and Cincinnati Bengals.",
  "prayers": [],
  "sources": [
    "https://en.wikipedia.org/wiki/Andy_Dalton",
    "Wikipedia (CC BY-SA) — text attribution required.",
    "https://en.wikipedia.org/wiki/Trevor_Siemian"
  ]
}
